django_presskit/__init__.py
django_presskit/admin.py
django_presskit/apps.py
django_presskit/models.py
django_presskit/urls.py
django_presskit/views.py
django_presskit/migrations/0001_initial.py
django_presskit/migrations/0002_auto_20181002_1847.py
django_presskit/migrations/0003_auto_20181002_1915.py
django_presskit/migrations/0004_auto_20190123_0157.py
django_presskit/migrations/0004_auto_20190202_2017.py
django_presskit/migrations/0005_merge_20190402_1106.py
django_presskit/migrations/__init__.py
django_presskit/static/django_presskit/django_presskit.css
django_presskit/templates/django_presskit/base.html
django_presskit/templates/django_presskit/company.html
django_presskit/templates/django_presskit/data.xml
django_presskit/templates/django_presskit/navitem.html
django_presskit/templates/django_presskit/no_default.html
django_presskit/templates/django_presskit/project.html
django_presskit/templatetags/__init__.py
django_presskit/templatetags/dpk_util.py
django_presskit-1.4.2.dist-info/licenses/LICENSE
tests/__init__.py
tests/settings.py
tests/test_dpk_util.py
tests/test_models.py
tests/test_views.py
tests/urls.py
django_presskit-1.4.2.dist-info/METADATA
django_presskit-1.4.2.dist-info/WHEEL
django_presskit-1.4.2.dist-info/top_level.txt
django_presskit-1.4.2.dist-info/RECORD
