Metadata-Version: 2.4
Name: django_presskit
Version: 1.4.2
Summary: A port of presskit() to Django
Home-page: https://github.com/FutureProofGames/django-presskit.git
Author: Future Proof Games
Author-email: info@futureproofgames.com
Classifier: Programming Language :: Python :: 3.8
Classifier: Framework :: Django :: 3.2
Classifier: License :: OSI Approved :: GNU General Public License v3 (GPLv3)
Classifier: Operating System :: OS Independent
License-File: LICENSE
Dynamic: author
Dynamic: author-email
Dynamic: classifier
Dynamic: description
Dynamic: description-content-type
Dynamic: home-page
Dynamic: license-file
Dynamic: summary
